{
    "version": "6032-20221014",
    "description": "mpv.net_CM 是基于 mpv.net 上游的中文分支模组",
    "homepage": "https://bbs.acgrip.com/thread-7798-1-1.html",
    "license": "GPL-2.0-only",
    "architecture": {
        "64bit": {
            "url": "https://github.com/hooke007/mpv.net_CM/releases/download/6032/mpvnet-CM-20221014.exe/#dl.7z",
            "hash": "dbf44524da09d5ac77ee082345da05301ec24832210f43f08cc6dc14e5ef06ba",
            "extract_dir": "mpvnet"
        }
    },
    "bin": "mpvnet.exe",
    "shortcuts": [
        [
            "mpvnet.exe",
            "mpvnet"
        ]
    ],
    "checkver": {
        "github": "https://github.com/hooke007/mpv.net_CM",
        "regex": "/releases/download/(?<tag>\\w+)/mpvnet-CM-(?<build>\\d{8})",
        "replace": "${tag}-${build}"
    },
    "autoupdate": {
        "architecture": {
            "64bit": {
                "url": "https://github.com/hooke007/mpv.net_CM/releases/download/$matchTag/mpvnet-CM-$matchBuild.exe/#dl.7z"
            }
        }
    }
}
