{
    "version": "3.31.2.441",
    "description": "一站式音视频会议解决方案",
    "homepage": "https://meeting.tencent.com/",
    "license": {
        "identifier": "Proprietary",
        "url": "https://meeting.tencent.com/declare.html"
    },
    "architecture": {
        "64bit": {
            "url": "https://updatecdn.meeting.qq.com/cos/edac8a100538bd8d2b0187ff5bc41471/TencentMeeting_0300000000_3.31.2.441_x86_64.publish.officialwebsite.exe#/dl.7z",
            "hash": "0b184aaa85ab6353aafe72de71e95736c49a619f08255008f53fa99625a20e9d"
        },
        "32bit": {
            "url": "https://updatecdn.meeting.qq.com/cos/e525667d95eae39bd315747cf3f1b1dd/TencentMeeting_0300000000_3.31.2.441.publish.officialwebsite.exe#/dl.7z",
            "hash": "15aa32726d1186d7accb3a2f40ed9dd5b611d9db9c57100618a0c4ba188bd4fb"
        }
    },
    "post_install": [
        "Get-ChildItem \"$dir\\`$_*\" | Rename-Item -NewName \"$version\" -Force",
        "Remove-Item \"$dir\\`$*\" -Recurse -Force -ErrorAction SilentlyContinue",
        "Remove-Item \"$dir\\wemeetapp_new.exe\" -Force -ErrorAction SilentlyContinue",
        "create_startmenu_shortcuts $manifest $original_dir $global $architecture",
        "$manifest.shortcuts = @()"
    ],
    "bin": [
        [
            "wemeetapp.exe",
            "tencent-meeting"
        ]
    ],
    "shortcuts": [
        [
            "wemeetapp.exe",
            "Tencent Meeting"
        ]
    ],
    "checkver": {
        "url": "https://meeting.tencent.com/web-service/query-download-info?q=[{\"package-type\":\"app\",\"channel\":\"0300000000\",\"platform\":\"windows\"},{\"package-type\":\"app\",\"channel\":\"0300000000\",\"arch\":\"x86_64\",\"platform\":\"windows\"}]&nonce=AAAAAAAAAAAAAAAA",
        "regex": "cos/(?<x86path>[\\w\\d]+)/TencentMeeting_(?<x86ch>[\\d]+)_(?<version>[\\d.]+)\\.publish\\.officialwebsite\\.exe.*cos/(?<x64path>[\\w\\d]+)/TencentMeeting_(?<x64ch>[\\d]+)_(?<version>[\\d.]+)(?<x64tail>[\\w\\d.]+)\\.exe"
    },
    "autoupdate": {
        "architecture": {
            "64bit": {
                "url": "https://updatecdn.meeting.qq.com/cos/$matchX64path/TencentMeeting_$matchX64ch_$version$matchX64tail.exe#/dl.7z"
            },
            "32bit": {
                "url": "https://updatecdn.meeting.qq.com/cos/$matchX86path/TencentMeeting_$matchX86ch_$version.publish.officialwebsite.exe#/dl.7z"
            }
        }
    },
    "notes": "We don't persist your Tencent Meeting data, they are still storaged in \"$env:APPDATA\\Tencent\\WeMeet\"."
}
